privision/__init__.py
privision/batch.py
privision/main.py
privision/server.py
privision/api/__init__.py
privision/api/task_queue.py
privision/config/__init__.py
privision/config/args.py
privision/core/__init__.py
privision/core/bbox_calculator.py
privision/core/blur.py
privision/core/detector_base.py
privision/core/detector_factory.py
privision/core/ocr_detector.py
privision/core/precise_locator.py
privision/core/video_processor.py
privision/core/detectors/__init__.py
privision/core/detectors/idcard_detector.py
privision/core/detectors/keyword_detector.py
privision/core/detectors/phone_detector.py
privision/test/__init__.py
privision/test/check_version.py
privision/test/debug_ocr_result.py
privision/test/test_batch.py
privision/test/test_ocr_and_detector.py
privision/test/test_ocr_basic.py
privision/test/test_ocr_call_count.py
privision/test/test_paddleocr_api.py
privision/test/test_phone_filter.py
privision/test/test_phone_positions.py
privision/test/test_single_frame.py
privision/test/test_smart_logic.py
privision/ui/__init__.py
privision/ui/progress.py
privision/ui/rich_ui.py
privision/ui/visualizer.py
privision-1.0.1.dist-info/licenses/LICENSE
privision-1.0.1.dist-info/METADATA
privision-1.0.1.dist-info/WHEEL
privision-1.0.1.dist-info/entry_points.txt
privision-1.0.1.dist-info/top_level.txt
privision-1.0.1.dist-info/RECORD
