Metadata-Version: 2.4
Name: privision
Version: 1.0.1
Summary: 视频内容脱敏工具 - 基于OCR的信息识别与打码系统
Author: 0xyk3r
License: MIT
Project-URL: Homepage, https://github.com/0xyk3r/Privision
Project-URL: Repository, https://github.com/0xyk3r/Privision
Project-URL: Issues, https://github.com/0xyk3r/Privision/issues
Keywords: privision,video,ocr,phone-number,mask,blur,privacy
Classifier: Development Status :: 4 - Beta
Classifier: Intended Audience :: Developers
Classifier: Intended Audience :: Information Technology
Classifier: Intended Audience :: End Users/Desktop
Classifier: Intended Audience :: Other Audience
Classifier: License :: OSI Approved :: MIT License
Classifier: Programming Language :: Python :: 3
Classifier: Programming Language :: Python :: 3.8
Classifier: Programming Language :: Python :: 3.9
Classifier: Programming Language :: Python :: 3.10
Classifier: Programming Language :: Python :: 3.11
Classifier: Programming Language :: Python :: 3.12
Classifier: Programming Language :: Python :: 3.13
Requires-Python: >=3.8
License-File: LICENSE
Requires-Dist: paddlepaddle>=3.0.0
Requires-Dist: paddleocr>=3.0.0
Requires-Dist: opencv-python>=4.8.0
Requires-Dist: numpy>=1.24.0
Requires-Dist: Pillow>=10.0.0
Requires-Dist: rich>=13.0.0
Requires-Dist: fastapi>=0.104.0
Requires-Dist: uvicorn>=0.24.0
Requires-Dist: python-multipart>=0.0.6
Requires-Dist: pydantic>=2.4.0
Provides-Extra: dev
Requires-Dist: pytest>=7.0.0; extra == "dev"
Requires-Dist: black>=23.0.0; extra == "dev"
Requires-Dist: flake8>=6.0.0; extra == "dev"
Dynamic: license-file
